requests_hawk/__init__.py
requests_hawk/tests/__init__.py
requests_hawk/tests/test_hawkauth.py
requests_hawk-1.1.1.dist-info/LICENSE.txt
requests_hawk-1.1.1.dist-info/METADATA
requests_hawk-1.1.1.dist-info/WHEEL
requests_hawk-1.1.1.dist-info/entry_points.txt
requests_hawk-1.1.1.dist-info/top_level.txt
requests_hawk-1.1.1.dist-info/RECORD
