Metadata-Version: 2.1
Name: requests-hawk
Version: 1.1.1
Summary: requests-hawk
Home-page: https://github.com/mozilla-services/requests-hawk
Author: Mozilla Services
Author-email: services-dev@mozilla.org
License: Apache License (2.0)
Keywords: authentication token hawk requests
Platform: UNKNOWN
Classifier: Intended Audience :: Developers
Classifier: Programming Language :: Python
Classifier: License :: OSI Approved :: Apache Software License
Classifier: Programming Language :: Python :: 2
Classifier: Programming Language :: Python :: 2.7
Classifier: Programming Language :: Python :: 3
Classifier: Programming Language :: Python :: 3.6
Classifier: Programming Language :: Python :: 3.7
Classifier: Programming Language :: Python :: 3.8
Requires-Dist: requests
Requires-Dist: mohawk
